{
  "default_config": {
    "steps": 16,
    "acc": "86"
  },
  "0": {
    "___": "1234567890123456",
    "kdr": "!!.....!..!!....",
    "sdr": "....!.......!...",
    "hhc": "!.!.!.!.!.!.!.!.",
    "sst": "...............!"
  },
  "1": {
    "___": "1234567890123456",
    "kdr": "!......!!.!.....",
    "sdr": "....!.......!...",
    "hhc": "..!.!.!.!.!.!.!."
  },
  "2": {
    "___": "1234567890123456",
    "kdr": "!.!.......!!...!",
    "sdr": "....!.......!...",
    "hhc": "!.!.!.!.!.!.!.!."
  },
  "3": {
    "___": "1234567890123456",
    "kdr": "!..!..!.!.......",
    "sdr": "....!.......!...",
    "bel": "..............!."
  },
  "4": {
    "___": "1234567890123456",
    "kdr": "!.!...!..!!.....",
    "sdr": "....!.......!...",
    "hhc": "!.!.!.!.!...!.!."
  }
}